pdftotext/__init__.py
pdftotext/pdf2text.py
pdftotext3-1.0.4.dist-info/METADATA
pdftotext3-1.0.4.dist-info/WHEEL
pdftotext3-1.0.4.dist-info/entry_points.txt
pdftotext3-1.0.4.dist-info/top_level.txt
pdftotext3-1.0.4.dist-info/RECORD
