Metadata-Version: 2.1
Name: pdftotext3
Version: 1.0.4
Summary: Convert PDF Files to Text Files using Google's Tesseract OCR.
Home-page: https://github.com/Anish-M-code/pdftotext
Author: Anish M
Author-email: aneesh25861@gmail.com
License: MIT LICENSE
Keywords: student project
Platform: UNKNOWN
Classifier: Development Status :: 5 - Production/Stable
Classifier: Intended Audience :: Developers
Classifier: Topic :: Software Development
Classifier: License :: OSI Approved :: MIT License
Classifier: Programming Language :: Python :: 3
Classifier: Intended Audience :: Developers
Classifier: Intended Audience :: Education
